lazyops-0.4.8.dist-info/licenses/LICENSE
lzl/README.md
lzl/__init__.py
lzl/version.py
lzl/api/__init__.py
lzl/api/aiohttpx/__init__.py
lzl/api/aiohttpx/abc.py
lzl/api/aiohttpx/api.py
lzl/api/aiohttpx/client.py
lzl/api/aiohttpx/presets.py
lzl/api/aiohttpx/types/__init__.py
lzl/api/aiohttpx/types/params.py
lzl/api/aiohttpx/types/typed.py
lzl/api/aiohttpx/utils/__init__.py
lzl/api/aiohttpx/utils/helpers.py
lzl/api/aiohttpx/utils/logs.py
lzl/api/aioreq/__init__.py
lzl/api/aioreq/api.py
lzl/api/aioreq/client.py
lzl/api/aioreq/exceptions.py
lzl/api/aioreq/utils.py
lzl/api/aiorqlite/__init__.py
lzl/api/aiorqlite/client.py
lzl/api/aiorqlite/connection.py
lzl/api/aiorqlite/cursor.py
lzl/api/aiorqlite/errors.py
lzl/api/aiorqlite/explain.py
lzl/api/aiorqlite/logging.py
lzl/api/aiorqlite/preprocessing.py
lzl/api/aiorqlite/result.py
lzl/api/aiorqlite/utils.py
lzl/api/aiorqlite2/__init__.py
lzl/api/aiorqlite2/connections.py
lzl/api/aiorqlite2/utils.py
lzl/api/argo/__init__.py
lzl/api/argo/events/__init__.py
lzl/api/argo/events/models.py
lzl/api/cloudflare/README.md
lzl/api/cloudflare/__init__.py
lzl/api/cloudflare/client.py
lzl/api/cloudflare/configs.py
lzl/api/cloudflare/models.py
lzl/api/cloudflare/types.py
lzl/api/cloudflare/resources/__init__.py
lzl/api/cloudflare/resources/dns.py
lzl/api/hatchet/__init__.py
lzl/api/hatchet/client.py
lzl/api/hatchet/config.py
lzl/api/hatchet/context.py
lzl/api/hatchet/session.py
lzl/api/hatchet/spawn.py
lzl/api/hatchet/state.py
lzl/api/hatchet/utils.py
lzl/api/hatchet/version.py
lzl/api/hatchet/worker.py
lzl/api/hatchet/_patches/_patcher.py
lzl/api/hatchet/_patches/context.j2.py
lzl/api/hatchet/_patches/current.j2.py
lzl/api/hatchet/_patches/ver_init.j2.py
lzl/api/hatchet/_patches/version.j2.py
lzl/api/hatchet/_patches/worker.j2.py
lzl/api/hatchet/v0320/client.py
lzl/api/hatchet/v0320/context.py
lzl/api/hatchet/v0320/session.py
lzl/api/hatchet/v0320/version.py
lzl/api/hatchet/v0320/worker.py
lzl/api/hatchet/workflow/__init__.py
lzl/api/hatchet/workflow/base.py
lazyops-0.4.8.dist-info/METADATA
lazyops-0.4.8.dist-info/WHEEL
lazyops-0.4.8.dist-info/entry_points.txt
lazyops-0.4.8.dist-info/top_level.txt
lazyops-0.4.8.dist-info/RECORD
