Metadata-Version: 2.4
Name: lazyops
Version: 0.4.8
Summary: A collection of submodules/patterns that are commonly used within Internal Development
Author-email: Tri Songz <ts@songzcorp.com>
License: MIT License
Classifier: Intended Audience :: Developers
Classifier: License :: OSI Approved :: MIT License
Classifier: Programming Language :: Python :: 3.10
Classifier: Programming Language :: Python :: 3.11
Classifier: Programming Language :: Python :: 3.12
Classifier: Topic :: Software Development :: Libraries
Requires-Python: >=3.10
License-File: LICENSE
Requires-Dist: loguru
Requires-Dist: pydantic>=2.0.0
Requires-Dist: pydantic-settings>=2.0.0
Requires-Dist: frozendict
Requires-Dist: async_lru
Requires-Dist: pyyaml
Requires-Dist: filelock
Requires-Dist: xxhash
Requires-Dist: anyio>=3.7.1
Requires-Dist: typer>=0.17.3
Requires-Dist: httpx>=0.28.1
Provides-Extra: kops
Requires-Dist: kubernetes; extra == "kops"
Requires-Dist: kubernetes_asyncio; extra == "kops"
Requires-Dist: kopf; extra == "kops"
Requires-Dist: aiocache; extra == "kops"
Requires-Dist: kr8s; extra == "kops"
Provides-Extra: fastapi
Requires-Dist: fastapi; extra == "fastapi"
Requires-Dist: uvicorn; extra == "fastapi"
Requires-Dist: python-multipart; extra == "fastapi"
Provides-Extra: builder
Requires-Dist: typer; extra == "builder"
Provides-Extra: openai
Requires-Dist: httpx; extra == "openai"
Requires-Dist: backoff; extra == "openai"
Requires-Dist: tiktoken; extra == "openai"
Requires-Dist: jinja2; extra == "openai"
Requires-Dist: pyyaml; extra == "openai"
Requires-Dist: numpy; extra == "openai"
Requires-Dist: scipy; extra == "openai"
Provides-Extra: fileio
Requires-Dist: botocore>=1.35.0; extra == "fileio"
Requires-Dist: boto3>=1.35.0; extra == "fileio"
Requires-Dist: aiobotocore>=2.15.0; extra == "fileio"
Requires-Dist: fsspec>=2024.10.0; extra == "fileio"
Requires-Dist: s3fs>=2024.10.0; extra == "fileio"
Requires-Dist: s3transfer>=0.10.0; extra == "fileio"
Requires-Dist: python-magic; extra == "fileio"
Requires-Dist: aiopath; extra == "fileio"
Requires-Dist: aiofiles; extra == "fileio"
Requires-Dist: aiofile; extra == "fileio"
Provides-Extra: file
Requires-Dist: botocore>=1.35.0; extra == "file"
Requires-Dist: boto3>=1.35.0; extra == "file"
Requires-Dist: aiobotocore>=2.15.0; extra == "file"
Requires-Dist: fsspec>=2024.10.0; extra == "file"
Requires-Dist: s3fs>=2024.10.0; extra == "file"
Requires-Dist: s3transfer>=0.10.0; extra == "file"
Requires-Dist: python-magic; extra == "file"
Requires-Dist: aiopath; extra == "file"
Requires-Dist: aiofiles; extra == "file"
Requires-Dist: aiofile; extra == "file"
Provides-Extra: docs
Requires-Dist: mkdocs>=1.5.0; extra == "docs"
Requires-Dist: mkdocs-material>=9.0.0; extra == "docs"
Requires-Dist: mkdocstrings[python]>=0.24.0; extra == "docs"
Requires-Dist: pymdown-extensions>=10.0; extra == "docs"
Provides-Extra: e2e
Requires-Dist: lazyops[dev,fastapi,file,kops,openai]; extra == "e2e"
Requires-Dist: kvdb-py; extra == "e2e"
Dynamic: license-file
